pdfkb/__init__.py
pdfkb/background_queue.py
pdfkb/config.py
pdfkb/document_processor.py
pdfkb/embeddings.py
pdfkb/embeddings_base.py
pdfkb/embeddings_factory.py
pdfkb/embeddings_huggingface.py
pdfkb/embeddings_local.py
pdfkb/embeddings_openai.py
pdfkb/exceptions.py
pdfkb/file_monitor.py
pdfkb/hybrid_search.py
pdfkb/intelligent_cache.py
pdfkb/main.py
pdfkb/models.py
pdfkb/reranker_base.py
pdfkb/reranker_deepinfra.py
pdfkb/reranker_factory.py
pdfkb/reranker_local.py
pdfkb/summarizer_base.py
pdfkb/summarizer_factory.py
pdfkb/summarizer_local.py
pdfkb/summarizer_remote.py
pdfkb/text_index.py
pdfkb/vector_store.py
pdfkb/web_server.py
pdfkb/chunker/__init__.py
pdfkb/chunker/chunker.py
pdfkb/chunker/chunker_langchain.py
pdfkb/chunker/chunker_page.py
pdfkb/chunker/chunker_semantic.py
pdfkb/chunker/chunker_unstructured.py
pdfkb/chunker/langchain_embeddings_wrapper.py
pdfkb/parsers/__init__.py
pdfkb/parsers/parser.py
pdfkb/parsers/parser_docling.py
pdfkb/parsers/parser_llm.py
pdfkb/parsers/parser_markdown.py
pdfkb/parsers/parser_marker.py
pdfkb/parsers/parser_mineru.py
pdfkb/parsers/parser_pymupdf4llm.py
pdfkb/parsers/parser_unstructured.py
pdfkb/parsers/templates/metadata_extraction.j2
pdfkb/parsers/templates/page_transcription.j2
pdfkb/web/__init__.py
pdfkb/web/middleware.py
pdfkb/web/server.py
pdfkb/web/websocket_handlers.py
pdfkb/web/models/__init__.py
pdfkb/web/models/web_models.py
pdfkb/web/services/__init__.py
pdfkb/web/services/web_document_service.py
pdfkb/web/services/web_search_service.py
pdfkb/web/services/web_status_service.py
pdfkb/web/services/websocket_manager.py
webui/README.md
webui/app.js
webui/index.html
webui/performance.js
webui/styles.css
webui/test_frontend.py
webui/components/DocumentDetail.js
webui/components/DocumentList.js
webui/components/FileUpload.js
webui/components/SearchInterface.js
webui/components/StatusBar.js
pdfkb_mcp-0.7.0.dist-info/METADATA
pdfkb_mcp-0.7.0.dist-info/WHEEL
pdfkb_mcp-0.7.0.dist-info/entry_points.txt
pdfkb_mcp-0.7.0.dist-info/licenses/LICENSE
pdfkb_mcp-0.7.0.dist-info/RECORD
