Metadata-Version: 2.4
Name: pdfkb-mcp
Version: 0.7.0
Summary: A Model Context Protocol server for managing PDF documents with vector search capabilities
Project-URL: Homepage, https://github.com/juanqui/pdfkb-mcp
Project-URL: Documentation, https://github.com/juanqui/pdfkb-mcp#readme
Project-URL: Repository, https://github.com/juanqui/pdfkb-mcp
Project-URL: Issues, https://github.com/juanqui/pdfkb-mcp/issues
Author-email: Juan Villa <juanqui@villafam.com>
License-Expression: MIT
License-File: LICENSE
Keywords: ai,chroma,embeddings,knowledge-base,mcp,openai,pdf,vector-search
Classifier: Development Status :: 3 - Alpha
Classifier: Intended Audience :: Developers
Classifier: Programming Language :: Python :: 3
Classifier: Programming Language :: Python :: 3.10
Classifier: Programming Language :: Python :: 3.11
Classifier: Programming Language :: Python :: 3.12
Classifier: Topic :: Scientific/Engineering :: Artificial Intelligence
Classifier: Topic :: Software Development :: Libraries :: Python Modules
Classifier: Topic :: Text Processing :: Indexing
Requires-Python: >=3.10
Requires-Dist: accelerate>=0.24.0
Requires-Dist: aiohttp>=3.9.0
Requires-Dist: chromadb>=1.0.15
Requires-Dist: fastapi>=0.104.0
Requires-Dist: fastmcp>=2.11.1
Requires-Dist: gguf>=0.17.0
Requires-Dist: huggingface-hub>=0.19.0
Requires-Dist: langchain-text-splitters>=0.3.9
Requires-Dist: openai>=1.99.1
Requires-Dist: pydantic>=2.5.0
Requires-Dist: pymupdf4llm>=0.0.27
Requires-Dist: pymupdf>=1.26.3
Requires-Dist: python-dotenv>=0.9.9
Requires-Dist: python-multipart>=0.0.6
Requires-Dist: safetensors>=0.4.0
Requires-Dist: torch>=2.0.0
Requires-Dist: transformers>=4.55.0
Requires-Dist: uvicorn[standard]>=0.24.0
Requires-Dist: watchdog>=6.0.0
Requires-Dist: websockets>=12.0
Requires-Dist: whoosh>=2.7.4
Requires-Dist: wsproto>=1.2.0
Provides-Extra: all
Requires-Dist: black>=24.8.0; extra == 'all'
Requires-Dist: bump2version>=1.0.0; extra == 'all'
Requires-Dist: docling>=2.43.0; extra == 'all'
Requires-Dist: easyocr>=1.7.2; extra == 'all'
Requires-Dist: flake8>=7.3.0; extra == 'all'
Requires-Dist: httpx>=0.28.1; extra == 'all'
Requires-Dist: isort>=6.0.0; extra == 'all'
Requires-Dist: jinja2>=3.1.6; extra == 'all'
Requires-Dist: langchain-text-splitters>=0.3.9; extra == 'all'
Requires-Dist: marker-pdf>=1.8.3; extra == 'all'
Requires-Dist: mineru[pipeline]>=2.1.10; extra == 'all'
Requires-Dist: mypy>=1.17.0; extra == 'all'
Requires-Dist: pillow>=10.1.0; extra == 'all'
Requires-Dist: pre-commit>=4.2.0; extra == 'all'
Requires-Dist: psutil>=6.0.0; extra == 'all'
Requires-Dist: pymupdf4llm>=0.0.27; extra == 'all'
Requires-Dist: pymupdf>=1.26.3; extra == 'all'
Requires-Dist: pytesseract>=0.3.13; extra == 'all'
Requires-Dist: pytest-asyncio>=1.1.0; extra == 'all'
Requires-Dist: pytest-cov>=6.0.0; extra == 'all'
Requires-Dist: pytest-mock>=3.14.0; extra == 'all'
Requires-Dist: pytest>=8.0.0; extra == 'all'
Requires-Dist: rapidocr-onnxruntime>=1.2.3; extra == 'all'
Requires-Dist: starlette>=0.27.0; extra == 'all'
Requires-Dist: types-aiofiles; extra == 'all'
Requires-Dist: unstructured>=0.18.11; extra == 'all'
Requires-Dist: unstructured[pdf]>=0.18.11; extra == 'all'
Requires-Dist: whoosh>=2.7.4; extra == 'all'
Provides-Extra: dev
Requires-Dist: black>=24.8.0; extra == 'dev'
Requires-Dist: bump2version>=1.0.0; extra == 'dev'
Requires-Dist: flake8>=7.3.0; extra == 'dev'
Requires-Dist: isort>=6.0.0; extra == 'dev'
Requires-Dist: mypy>=1.17.0; extra == 'dev'
Requires-Dist: pre-commit>=4.2.0; extra == 'dev'
Requires-Dist: pytest-asyncio>=1.1.0; extra == 'dev'
Requires-Dist: pytest-cov>=6.0.0; extra == 'dev'
Requires-Dist: pytest-mock>=3.14.0; extra == 'dev'
Requires-Dist: pytest>=8.0.0; extra == 'dev'
Requires-Dist: types-aiofiles; extra == 'dev'
Provides-Extra: docling
Requires-Dist: docling>=2.43.0; extra == 'docling'
Provides-Extra: docling-complete
Requires-Dist: docling>=2.43.0; extra == 'docling-complete'
Requires-Dist: easyocr>=1.7.2; extra == 'docling-complete'
Requires-Dist: pytesseract>=0.3.13; extra == 'docling-complete'
Requires-Dist: rapidocr-onnxruntime>=1.2.3; extra == 'docling-complete'
Provides-Extra: hybrid
Requires-Dist: whoosh>=2.7.4; extra == 'hybrid'
Provides-Extra: langchain
Requires-Dist: langchain-text-splitters>=0.3.9; extra == 'langchain'
Provides-Extra: llm
Requires-Dist: httpx>=0.28.1; extra == 'llm'
Requires-Dist: jinja2>=3.1.6; extra == 'llm'
Requires-Dist: pillow>=10.1.0; extra == 'llm'
Requires-Dist: pymupdf>=1.26.3; extra == 'llm'
Provides-Extra: local-embeddings
Requires-Dist: accelerate>=0.24.0; extra == 'local-embeddings'
Requires-Dist: huggingface-hub>=0.19.0; extra == 'local-embeddings'
Requires-Dist: safetensors>=0.4.0; extra == 'local-embeddings'
Requires-Dist: torch>=2.0.0; extra == 'local-embeddings'
Requires-Dist: transformers>=4.55.0; extra == 'local-embeddings'
Provides-Extra: marker
Requires-Dist: marker-pdf>=1.8.3; extra == 'marker'
Provides-Extra: mineru
Requires-Dist: mineru[pipeline]>=2.1.10; extra == 'mineru'
Provides-Extra: pymupdf4llm
Requires-Dist: pymupdf4llm>=0.0.27; extra == 'pymupdf4llm'
Provides-Extra: semantic
Requires-Dist: langchain-experimental>=0.3.0; extra == 'semantic'
Requires-Dist: langchain-text-splitters>=0.3.9; extra == 'semantic'
Provides-Extra: unstructured
Requires-Dist: unstructured[pdf]>=0.18.11; extra == 'unstructured'
Provides-Extra: unstructured-chunker
Requires-Dist: unstructured>=0.18.11; extra == 'unstructured-chunker'
Provides-Extra: web
Requires-Dist: psutil>=6.0.0; extra == 'web'
Requires-Dist: starlette>=0.27.0; extra == 'web'
